[
    {
        "name": "angry.png",
        "type": ".PNG file",
        "size": "580.63 KB",
        "dateModified": 1710507006.0
    },
    {
        "name": "clap.png",
        "type": ".PNG file",
        "size": "538.64 KB",
        "dateModified": 1710507016.0
    },
    {
        "name": "confetty.png",
        "type": ".PNG file",
        "size": "648.13 KB",
        "dateModified": 1710506988.0
    },
    {
        "name": "cookie.png",
        "type": ".PNG file",
        "size": "483.83 KB",
        "dateModified": 1710507034.0
    },
    {
        "name": "cozy.png",
        "type": ".PNG file",
        "size": "477.98 KB",
        "dateModified": 1710507052.0
    },
    {
        "name": "drink.png",
        "type": ".PNG file",
        "size": "506.97 KB",
        "dateModified": 1710507092.0
    },
    {
        "name": "excited.png",
        "type": ".PNG file",
        "size": "550.77 KB",
        "dateModified": 1710506998.0
    },
    {
        "name": "GG.png",
        "type": ".PNG file",
        "size": "495.78 KB",
        "dateModified": 1710507074.0
    },
    {
        "name": "heart.png",
        "type": ".PNG file",
        "size": "491.20 KB",
        "dateModified": 1710507100.0
    },
    {
        "name": "pat.png",
        "type": ".PNG file",
        "size": "508.33 KB",
        "dateModified": 1710507064.0
    },
    {
        "name": "peek.png",
        "type": ".PNG file",
        "size": "503.59 KB",
        "dateModified": 1710507044.0
    },
    {
        "name": "yikes.png",
        "type": ".PNG file",
        "size": "566.18 KB",
        "dateModified": 1710507026.0
    }
]