[
    {
        "name": "angry.png",
        "type": ".PNG file",
        "size": "5.19 KB",
        "dateModified": 1689966268.0
    },
    {
        "name": "clap.png",
        "type": ".PNG file",
        "size": "5.16 KB",
        "dateModified": 1689966268.0
    },
    {
        "name": "GG.png",
        "type": ".PNG file",
        "size": "5.34 KB",
        "dateModified": 1689966268.0
    },
    {
        "name": "gun.png",
        "type": ".PNG file",
        "size": "5.05 KB",
        "dateModified": 1689966268.0
    },
    {
        "name": "laugh new.png",
        "type": ".PNG file",
        "size": "5.15 KB",
        "dateModified": 1689966268.0
    },
    {
        "name": "laugh.png",
        "type": ".PNG file",
        "size": "5.10 KB",
        "dateModified": 1689966268.0
    },
    {
        "name": "ok.png",
        "type": ".PNG file",
        "size": "5.15 KB",
        "dateModified": 1689966268.0
    },
    {
        "name": "please.png",
        "type": ".PNG file",
        "size": "2.63 KB",
        "dateModified": 1690505590.0
    },
    {
        "name": "popcorn.png",
        "type": ".PNG file",
        "size": "5.21 KB",
        "dateModified": 1689966270.0
    },
    {
        "name": "pray.png",
        "type": ".PNG file",
        "size": "1.86 KB",
        "dateModified": 1690492244.0
    },
    {
        "name": "shock.png",
        "type": ".PNG file",
        "size": "5.40 KB",
        "dateModified": 1689966270.0
    },
    {
        "name": "sulk.png",
        "type": ".PNG file",
        "size": "5.17 KB",
        "dateModified": 1689966268.0
    },
    {
        "name": "think.png",
        "type": ".PNG file",
        "size": "5.21 KB",
        "dateModified": 1689966268.0
    }
]